{"type": "Feature", "id": 12514218, "geometry": {"type": "Point", "coordinates": [126.8694, 37.597198]}, "properties": {"woe:id": 12514218, "woe:parent_id": 28997209, "woe:name": "R 113 Airport", "woe:placetype": 14, "woe:placetype_name": "Airport", "woe:lang": "ENG", "iso:country": "KR", "meta:provider": ["geoplanet:7.3.1", "geoplanet:7.3.2", "geoplanet:7.4.0", "geoplanet:7.4.1", "geoplanet:7.5.1", "geoplanet:7.5.2", "geoplanet:7.6.0", "geoplanet:7.8.1", "geoplanet:7.9.0", "geoplanet:7.10.0", "geoplanet:8.0.0", "woeplanet:8.0.0"], "meta:indexed": "2020-08-20T20:20:46.921181", "meta:updated": "2020-10-14T11:33:29.418639", "woe:hierarchy": {"continent": 24865671, "country": 23424868, "town": 0, "planet": 1, "county": 28289179, "suburb": 0, "state": 2345969, "region": 0, "localadmin": 28997209}, "woe:timezone_id": 28350854, "woe:hash": "wydjyur7x39j", "woe:centroid": [126.8694, 37.597198], "geom:latitude": 37.597198, "geom:longitude": 126.8694, "geom:hash": "wydjyur7x39j", "woe:latitude": 37.597198, "geom:centroid": [126.8694, 37.597198], "woe:longitude": 126.8694, "woe:repo": "woeplanet-airport-kr", "geom:area": 0.0, "woe:scale": 19}}