{"type": "Feature", "id": 12514215, "properties": {"woe:id": 12514215, "woe:parent_id": 28806432, "woe:name": "Paengnyong do Airport", "woe:placetype": 14, "woe:placetype_name": "Airport", "woe:lang": "ENG", "iso:country": "KR", "meta:provider": ["geoplanet:7.3.1", "geoplanet:7.3.2", "geoplanet:7.4.0", "geoplanet:7.4.1", "geoplanet:7.5.1", "geoplanet:7.5.2", "geoplanet:7.6.0", "geoplanet:7.8.1", "geoplanet:7.9.0", "geoplanet:7.10.0", "geoplanet:8.0.0", "woeplanet:8.0.0"], "meta:indexed": "2020-08-20T20:20:46.918715", "meta:updated": "2020-08-22T02:51:24.483825", "woe:hierarchy": {"continent": 24865671, "country": 23424868, "town": 0, "planet": 1, "county": 28289263, "suburb": 0, "state": 20069922, "region": 0, "localadmin": 28806432}, "woe:timezone_id": 28350854, "woe:hash": "wy8xynfk0mer", "woe:centroid": [124.719902, 37.962601], "geom:latitude": 37.962601, "geom:longitude": 124.719902, "geom:hash": "wy8xynfk0mer", "woe:latitude": 37.962601, "geom:centroid": [124.719902, 37.962601], "woe:longitude": 124.719902, "woe:repo": "woeplanet-airport-kr"}, "geometry": {"coordinates": [124.719902, 37.962601], "type": "Point"}}