{"type": "Feature", "id": 12523361, "geometry": {"type": "Point", "coordinates": [126.53009, 33.50631]}, "properties": {"woe:id": 12523361, "woe:parent_id": 28808921, "woe:name": "Chu Ja Heliport", "woe:placetype": 14, "woe:placetype_name": "Airport", "woe:lang": "ENG", "iso:country": "KR", "meta:provider": ["geoplanet:7.3.1", "geoplanet:7.3.2", "geoplanet:7.4.0", "geoplanet:7.4.1", "geoplanet:7.5.1", "geoplanet:7.5.2", "geoplanet:7.6.0", "geoplanet:7.8.1", "geoplanet:7.9.0", "geoplanet:7.10.0", "geoplanet:8.0.0", "woeplanet:8.0.0"], "meta:indexed": "2020-08-20T20:20:46.938400", "woe:alias_ENG_V": ["JCJ", "JCJ Airport"], "meta:updated": "2020-10-14T11:33:29.411500", "woe:hierarchy": {"continent": 24865671, "country": 23424868, "town": 0, "planet": 1, "county": 28289128, "suburb": 0, "state": 2345963, "region": 0, "localadmin": 28808921}, "woe:timezone_id": 28350854, "woe:hash": "wvcyx78kkuck", "woe:centroid": [126.53009, 33.50631], "geom:latitude": 33.50631, "geom:longitude": 126.53009, "geom:hash": "wvcyx78kkuck", "woe:latitude": 33.50631, "geom:centroid": [126.53009, 33.50631], "woe:longitude": 126.53009, "woe:repo": "woeplanet-airport-kr", "geom:area": 0.0, "woe:scale": 19}}