{"type": "Feature", "id": 12514225, "geometry": {"type": "Point", "coordinates": [128.699402, 35.1381]}, "properties": {"woe:id": 12514225, "woe:parent_id": 28808694, "woe:name": "R 813 Airport", "woe:placetype": 14, "woe:placetype_name": "Airport", "woe:lang": "ENG", "iso:country": "KR", "meta:provider": ["geoplanet:7.3.1", "geoplanet:7.3.2", "geoplanet:7.4.0", "geoplanet:7.4.1", "geoplanet:7.5.1", "geoplanet:7.5.2", "geoplanet:7.6.0", "geoplanet:7.8.1", "geoplanet:7.9.0", "geoplanet:7.10.0", "geoplanet:8.0.0", "woeplanet:8.0.0"], "meta:indexed": "2020-08-20T20:20:46.927441", "meta:updated": "2020-10-14T11:33:29.419399", "woe:hierarchy": {"continent": 24865671, "country": 23424868, "town": 0, "planet": 1, "county": 28289223, "suburb": 0, "state": 2345967, "region": 0, "localadmin": 28808694}, "woe:timezone_id": 28350854, "woe:hash": "wy5xbssn32te", "woe:centroid": [128.699402, 35.1381], "geom:latitude": 35.1381, "geom:longitude": 128.699402, "geom:hash": "wy5xbssn32te", "woe:latitude": 35.1381, "geom:centroid": [128.699402, 35.1381], "woe:longitude": 128.699402, "woe:repo": "woeplanet-airport-kr", "geom:area": 0.0, "woe:scale": 19}}